{
  "providers": [
    {
      "id": 1,
      "name": "OVH",
      "website": "https://www.ovh.it/",
      "label": "#3d557b"
    },
    {
      "id": 2,
      "name": "Aruba",
      "website": "https://www.aruba.it/",
      "label": "#ff0000"
    },
    {
      "id": 3,
      "name": "Media Temple 3",
      "website": "https://mediatemple.net/",
      "label": "#666666"
    }
  ],
  "domains": [
    {
      "url": "www.erica2222222.com",
      "domain": {
        "id": 2,
        "name": "Aruba",
        "website": "https://www.aruba.it/",
        "label": "#ff0000"
      },
      "hosting": {
        "id": 2,
        "name": "Aruba",
        "website": "https://www.aruba.it/",
        "label": "#ff0000"
      },
      "renewal": "12/15/2017",
      "fee": "400.6",
      "pay": "0",
      "note": "rgrtgrt",
      "id": 4
    }
  ]
}